MANIFEST.in
README.rst
setup.py
task1_mareev_meledin/__init__.py
task1_mareev_meledin/solve с коментами.py
task1_mareev_meledin/solve.py
task1_mareev_meledin.egg-info/PKG-INFO
task1_mareev_meledin.egg-info/SOURCES.txt
task1_mareev_meledin.egg-info/dependency_links.txt
task1_mareev_meledin.egg-info/not-zip-safe
task1_mareev_meledin.egg-info/requires.txt
task1_mareev_meledin.egg-info/top_level.txt