Metadata-Version: 1.1
Name: task1-mareev-meledin
Version: 4.2
Summary: Workshop 3 course. Autumn 17-18. Exercise 1.
Home-page: https://github.com/GlebOlegovich/prac-2017-2018/tree/task1-mareev-meledin/submissions/task1/mareev-meledin/task1_mareev_meledin
Author: Mareev Gleb and Meledin Stanislav
Author-email: wowmagic.gm@gmail.com
License: MIT
Keywords: task1 mareev maledin cs msu
Platform: UNKNOWN
Classifier: Development Status :: 5 - Production/Stable
Classifier: License :: OSI Approved :: MIT License
Classifier: Programming Language :: Python :: 3.6
Classifier: Topic :: Scientific/Engineering :: Mathematics
